LICENSE
reComBat/.DS_Store
reComBat/__init__.py
reComBat/cli.py
reComBat/reComBat.py
reComBat/src/reComBat_single_class.py
reComBat/src/utils.py
recombat-0.1.4.dist-info/entry_points.txt
recombat-0.1.4.dist-info/LICENSE
recombat-0.1.4.dist-info/WHEEL
recombat-0.1.4.dist-info/METADATA
recombat-0.1.4.dist-info/RECORD
