Metadata-Version: 2.1
Name: recombat
Version: 0.1.4
Summary: regularised ComBat method to correct batch effects
Home-page: https://github.com/BorgwardtLab/reComBat
License: BSD-3-Clause
Keywords: combat,recombat,batch correction
Author: Michael F. Adamer
Author-email: mikeadamer@gmail.com
Requires-Python: >=3.8,<3.11
Classifier: License :: OSI Approved :: BSD License
Classifier: Programming Language :: Python :: 3
Classifier: Programming Language :: Python :: 3.10
Classifier: Programming Language :: Python :: 3.8
Classifier: Programming Language :: Python :: 3.9
Requires-Dist: fire (>=0.4.0,<0.5.0)
Requires-Dist: numpy (>=1.20.0,<2.0.0)
Requires-Dist: pandas (>=1.3.4,<2.0.0)
Requires-Dist: sklearn (>=0.0,<0.1)
Requires-Dist: tqdm (>=4.62.3,<5.0.0)
Project-URL: Repository, https://github.com/BorgwardtLab/reComBat
